makedb/__init__.py
makedb-0.1.0.dist-info/METADATA
makedb-0.1.0.dist-info/WHEEL
makedb-0.1.0.dist-info/top_level.txt
makedb-0.1.0.dist-info/RECORD
