Metadata-Version: 2.4
Name: makedb
Version: 0.1.0
Summary: makedb is the first Python library built to create and continuously evolve relational database schemas through live, incrementally completed ER diagrams. It transforms traditional database modeling into an iterative, automated, and developer-friendly process. Whether you're prototyping fast, managing complex migrations, or building low-code tools, makedb doesn’t just draw your data—it evolves it with you.
Author: Adriana Abad
License: MIT
Requires-Python: >=3.7
